Pillow541ZhongwenWendang/README.md
Pillow541ZhongwenWendang/__init__.py
Pillow541ZhongwenWendang/__main__.py
Pillow541ZhongwenWendang/file.epub
Pillow541ZhongwenWendang/index.html
Pillow541ZhongwenWendang/css/__init__.py
Pillow541ZhongwenWendang/css/annotations.css
Pillow541ZhongwenWendang/css/main.css
Pillow541ZhongwenWendang/css/normalize.css
Pillow541ZhongwenWendang/css/popup.css
Pillow541ZhongwenWendang/font/__init__.py
Pillow541ZhongwenWendang/font/fontello.eot
Pillow541ZhongwenWendang/font/fontello.svg
Pillow541ZhongwenWendang/font/fontello.ttf
Pillow541ZhongwenWendang/font/fontello.woff
Pillow541ZhongwenWendang/img/__init__.py
Pillow541ZhongwenWendang/img/annotator-glyph-sprite.png
Pillow541ZhongwenWendang/img/annotator-icon-sprite.png
Pillow541ZhongwenWendang/img/apple-touch-icon.png
Pillow541ZhongwenWendang/img/cancelfullscreen.png
Pillow541ZhongwenWendang/img/close.png
Pillow541ZhongwenWendang/img/fullscreen.png
Pillow541ZhongwenWendang/img/loader.gif
Pillow541ZhongwenWendang/img/menu-icon.png
Pillow541ZhongwenWendang/img/save.png
Pillow541ZhongwenWendang/img/saved.png
Pillow541ZhongwenWendang/img/settings-s.png
Pillow541ZhongwenWendang/img/settings.png
Pillow541ZhongwenWendang/img/star.png
Pillow541ZhongwenWendang/js/__init__.py
Pillow541ZhongwenWendang/js/epub.js
Pillow541ZhongwenWendang/js/epub.min.js
Pillow541ZhongwenWendang/js/epub.min.map
Pillow541ZhongwenWendang/js/hooks.min.js
Pillow541ZhongwenWendang/js/hooks.min.map
Pillow541ZhongwenWendang/js/reader.js
Pillow541ZhongwenWendang/js/reader.js.map
Pillow541ZhongwenWendang/js/reader.min.js
Pillow541ZhongwenWendang/js/reader.min.map
Pillow541ZhongwenWendang/js/hooks/__init__.py
Pillow541ZhongwenWendang/js/hooks/extensions/__init__.py
Pillow541ZhongwenWendang/js/hooks/extensions/highlight.js
Pillow541ZhongwenWendang/js/libs/__init__.py
Pillow541ZhongwenWendang/js/libs/jquery.min.js
Pillow541ZhongwenWendang/js/libs/localforage.min.js
Pillow541ZhongwenWendang/js/libs/screenfull.js
pillow_5_4_1_zhongwen_wendang-2024.3.4.0.dist-info/METADATA
pillow_5_4_1_zhongwen_wendang-2024.3.4.0.dist-info/WHEEL
pillow_5_4_1_zhongwen_wendang-2024.3.4.0.dist-info/entry_points.txt
pillow_5_4_1_zhongwen_wendang-2024.3.4.0.dist-info/top_level.txt
pillow_5_4_1_zhongwen_wendang-2024.3.4.0.dist-info/RECORD
